FoldToZip/__init__.py
FoldToZip/foldtozip.py
foldtozip-0.0.2.dist-info/METADATA
foldtozip-0.0.2.dist-info/WHEEL
foldtozip-0.0.2.dist-info/top_level.txt
foldtozip-0.0.2.dist-info/RECORD
