Metadata-Version: 2.1
Name: foldtozip
Version: 0.0.2
Summary: No description
Home-page: https://github.com/TheGamer548/FoldToZipt
Author: Coder100
Author-email: jacobhason86@gmail.coù
Project-URL: Source-code, https://github.com/TheGamer548/Pikkit
Classifier: Programming Language :: Python :: 3
Classifier: License :: OSI Approved :: MIT License
Classifier: Operating System :: OS Independent
Requires-Python: >=3.6
